sqlalchemy_cockroachdb/__init__.py
sqlalchemy_cockroachdb/_psycopg_common.py
sqlalchemy_cockroachdb/asyncpg.py
sqlalchemy_cockroachdb/base.py
sqlalchemy_cockroachdb/ddl_compiler.py
sqlalchemy_cockroachdb/provision.py
sqlalchemy_cockroachdb/psycopg2.py
sqlalchemy_cockroachdb/requirements.py
sqlalchemy_cockroachdb/stmt_compiler.py
sqlalchemy_cockroachdb/transaction.py
sqlalchemy_cockroachdb-2.0.1.dist-info/LICENSE
sqlalchemy_cockroachdb-2.0.1.dist-info/METADATA
sqlalchemy_cockroachdb-2.0.1.dist-info/WHEEL
sqlalchemy_cockroachdb-2.0.1.dist-info/entry_points.txt
sqlalchemy_cockroachdb-2.0.1.dist-info/top_level.txt
sqlalchemy_cockroachdb-2.0.1.dist-info/RECORD
