Metadata-Version: 2.1
Name: sqlalchemy-cockroachdb
Version: 2.0.1
Summary: CockroachDB dialect for SQLAlchemy
Home-page: https://github.com/cockroachdb/sqlalchemy-cockroachdb
Author: Cockroach Labs
Author-email: cockroach-db@googlegroups.com
License: http://www.apache.org/licenses/LICENSE-2.0
Project-URL: Documentation, https://github.com/cockroachdb/sqlalchemy-cockroachdb/wiki
Project-URL: Source, https://github.com/cockroachdb/sqlalchemy-cockroachdb
Project-URL: Tracker, https://github.com/cockroachdb/sqlalchemy-cockroachdb/issues
Keywords: SQLAlchemy CockroachDB
Classifier: License :: OSI Approved :: Apache Software License
Classifier: Programming Language :: Python :: 3
Classifier: Programming Language :: Python :: 3 :: Only
Classifier: Programming Language :: Python :: 3.8
Classifier: Programming Language :: Python :: 3.9
Classifier: Programming Language :: Python :: 3.10
Classifier: Programming Language :: Python :: 3.11
License-File: LICENSE
